castaway/__init__.py
castaway-1.1.0.dist-info/LICENSE
castaway-1.1.0.dist-info/METADATA
castaway-1.1.0.dist-info/WHEEL
castaway-1.1.0.dist-info/top_level.txt
castaway-1.1.0.dist-info/RECORD
