Metadata-Version: 2.2
Name: castaway
Version: 1.1.0
Summary: Simple wrapper for dotenv, with casting
Author-email: David Krauth <dakrauth@gmail.com>
License: MIT License
Project-URL: Homepage, http://github.com/dakrauth/castaway
Classifier: Development Status :: 5 - Production/Stable
Classifier: Environment :: Web Environment
Classifier: Environment :: Console
Classifier: Framework :: Django
Classifier: License :: OSI Approved :: MIT License
Classifier: Programming Language :: Python
Classifier: Programming Language :: Python :: 3 :: Only
Classifier: Programming Language :: Python :: 3.10
Classifier: Programming Language :: Python :: 3.11
Classifier: Programming Language :: Python :: 3.12
Classifier: Programming Language :: Python :: 3.13
Requires-Python: >=3.10
License-File: LICENSE
Requires-Dist: python-dotenv[cli]==1.0.1
Provides-Extra: django
Requires-Dist: dj-email-url==1.0.6; extra == "django"
Requires-Dist: dj-database-url==2.3.0; extra == "django"
Provides-Extra: test
Requires-Dist: pytest-cov; extra == "test"
Requires-Dist: tox; extra == "test"
